wagtail_headers_footers/__init__.py
wagtail_headers_footers/models.py
wagtail_headers_footers/migrations/0001_initial.py
wagtail_headers_footers/migrations/__init__.py
wagtail_headers_footers/templatetags/__init__.py
wagtail_headers_footers/templatetags/header_footer_tags.py
wagtail_headers_footers-0.1.3.dist-info/licenses/LICENSE
wagtail_headers_footers-0.1.3.dist-info/METADATA
wagtail_headers_footers-0.1.3.dist-info/WHEEL
wagtail_headers_footers-0.1.3.dist-info/top_level.txt
wagtail_headers_footers-0.1.3.dist-info/RECORD
