Metadata-Version: 2.4
Name: wagtail-headers-footers
Version: 0.1.3
Summary: Reusable Wagtail app to manage header and footer scripts sitewide and per-page.
Author-email: Malvin Ndip <23006212+DazzyMlv@users.noreply.github.com>
License: MIT
Project-URL: Homepage, https://github.com/dazzymlv/wagtail-headers-footers
Project-URL: source, https://github.com/dazzymlv/wagtail-headers-footers.git
Project-URL: changelog, https://github.com/dazzymlv/wagtail-headers-footers/CHANGELOG.md
Project-URL: issues, https://github.com/dazzymlv/wagtail-headers-footers/issues
Project-URL: documentation, https://github.com/dazzymlv/wagtail-headers-footers/README.md
Keywords: wagtail,headers,footers,django,malvin ndip
Classifier: Development Status :: 3 - Alpha
Classifier: Environment :: Web Environment
Classifier: Framework :: Django
Classifier: Framework :: Django :: 5.2
Classifier: Framework :: Wagtail
Classifier: Framework :: Wagtail :: 6
Classifier: Framework :: Wagtail :: 7
Classifier: Framework :: tox
Classifier: Intended Audience :: Developers
Classifier: Intended Audience :: Information Technology
Classifier: Intended Audience :: System Administrators
Classifier: License :: OSI Approved :: MIT License
Classifier: Natural Language :: English
Classifier: Operating System :: OS Independent
Classifier: Programming Language :: Python
Classifier: Programming Language :: Python :: 3
Classifier: Programming Language :: Python :: 3 :: Only
Classifier: Programming Language :: Python :: 3.12
Classifier: Programming Language :: Python :: 3.13
Classifier: Topic :: Software Development
Classifier: Topic :: Software Development :: Libraries
Classifier: Topic :: Software Development :: Libraries :: Python Modules
Classifier: Topic :: System :: Installation/Setup
Classifier: Topic :: System :: Software Distribution
Classifier: Typing :: Typed
Requires-Python: >=3.12
License-File: LICENSE
Requires-Dist: wagtail>=6.4.0
Dynamic: license-file
